{"files":{"packages/shared/dist/schemas/auth.d.ts.map":{"size":567,"mtime_nanos":1783332897743405251,"mode":436,"is_dir":false},"packages/shared/dist/schemas/platform.d.ts.map":{"size":624,"mtime_nanos":1783332897780397521,"mode":436,"is_dir":false},"packages/shared/dist/schemas/file.d.ts.map":{"size":483,"mtime_nanos":1783332897766397483,"mode":436,"is_dir":false},"packages/shared/dist/schemas/index.js.map":{"size":300,"mtime_nanos":1783332897800397575,"mode":436,"is_dir":false},"packages/shared/dist/schemas/platform.d.ts":{"size":1334,"mtime_nanos":1783332823497198436,"mode":436,"is_dir":false},"packages/shared/dist/schemas/report.d.ts.map":{"size":371,"mtime_nanos":1783332897787397540,"mode":436,"is_dir":false},"packages/shared/dist/schemas/ai.js":{"size":885,"mtime_nanos":1783332897791397550,"mode":436,"is_dir":false},"packages/shared/dist/types/index.d.ts.map":{"size":2064,"mtime_nanos":1783332897804397585,"mode":436,"is_dir":false},"packages/shared/dist/schemas/index.d.ts":{"size":292,"mtime_nanos":1783320793388005022,"mode":436,"is_dir":false},"packages/shared/dist/schemas/platform.js.map":{"size":1274,"mtime_nanos":1783332897776397510,"mode":436,"is_dir":false},"packages/shared/dist/schemas/file.js":{"size":615,"mtime_nanos":1783332897763397475,"mode":436,"is_dir":false},"packages/shared/.turbo/turbo-build.log":{"size":36,"mtime_nanos":1783341196068211205,"mode":436,"is_dir":false},"packages/shared/dist/schemas/auth.d.ts":{"size":981,"mtime_nanos":1783320793369004932,"mode":436,"is_dir":false},"packages/shared/dist/schemas/report.js.map":{"size":680,"mtime_nanos":1783332897785397534,"mode":436,"is_dir":false},"packages/shared/dist/schemas/memory.js":{"size":510,"mtime_nanos":1783332897782397526,"mode":436,"is_dir":false},"packages/shared/dist/schemas/voice.js.map":{"size":713,"mtime_nanos":1783332897771823629,"mode":436,"is_dir":false},"packages/shared/dist/types/index.js.map":{"size":111,"mtime_nanos":1783332897802397580,"mode":436,"is_dir":false},"packages/shared/dist/schemas/memory.d.ts":{"size":976,"mtime_nanos":1783320793381004989,"mode":436,"is_dir":false},"packages/shared/dist/index.d.ts":{"size":71,"mtime_nanos":1783320793388005022,"mode":436,"is_dir":false},"packages/shared/dist/schemas/file.js.map":{"size":944,"mtime_nanos":1783332897762397472,"mode":436,"is_dir":false},"packages/shared/dist/schemas/message.js.map":{"size":1579,"mtime_nanos":1783332897746094397,"mode":436,"is_dir":false},"packages/shared/dist/schemas/memory.js.map":{"size":814,"mtime_nanos":1783332897781397523,"mode":436,"is_dir":false},"packages/shared/dist/schemas/ai.d.ts.map":{"size":479,"mtime_nanos":1783332897793397556,"mode":436,"is_dir":false},"packages/shared/dist/schemas/message.d.ts.map":{"size":602,"mtime_nanos":1783332897759397464,"mode":436,"is_dir":false},"packages/shared/dist/schemas/voice.d.ts":{"size":776,"mtime_nanos":1783320793377004970,"mode":436,"is_dir":false},"packages/shared/dist/schemas/settings.d.ts":{"size":923,"mtime_nanos":1783320793387005018,"mode":436,"is_dir":false},"packages/shared/dist/schemas/message.js":{"size":1026,"mtime_nanos":1783332897746345356,"mode":436,"is_dir":false},"packages/shared/dist/schemas/ai.js.map":{"size":1439,"mtime_nanos":1783332897791397550,"mode":436,"is_dir":false},"packages/shared/dist/schemas/platform.js":{"size":882,"mtime_nanos":1783332897777397513,"mode":436,"is_dir":false},"packages/shared/dist/schemas/auth.js":{"size":589,"mtime_nanos":1783332897741247018,"mode":436,"is_dir":false},"packages/shared/dist/schemas/settings.d.ts.map":{"size":470,"mtime_nanos":1783332897799397572,"mode":436,"is_dir":false},"packages/shared/dist/index.js.map":{"size":123,"mtime_nanos":1783332897801397577,"mode":436,"is_dir":false},"packages/shared/dist/schemas/index.d.ts.map":{"size":302,"mtime_nanos":1783332897801397577,"mode":436,"is_dir":false},"packages/shared/dist/index.js":{"size":69,"mtime_nanos":1783332897801397577,"mode":436,"is_dir":false},"packages/shared/dist/schemas/report.d.ts":{"size":669,"mtime_nanos":1783320793382004994,"mode":436,"is_dir":false},"packages/shared/dist/schemas/settings.js":{"size":696,"mtime_nanos":1783332897797397566,"mode":436,"is_dir":false},"packages/shared/dist/types/index.d.ts":{"size":2304,"mtime_nanos":1783320793390005032,"mode":436,"is_dir":false},"packages/shared/dist/index.d.ts.map":{"size":125,"mtime_nanos":1783332897801397577,"mode":436,"is_dir":false},"packages/shared/dist/schemas/ai.d.ts":{"size":1125,"mtime_nanos":1783320793384005003,"mode":436,"is_dir":false},"packages/shared/dist/schemas/voice.js":{"size":459,"mtime_nanos":1783332897771823629,"mode":436,"is_dir":false},"packages/shared/dist/types/index.js":{"size":44,"mtime_nanos":1783332897802397580,"mode":436,"is_dir":false},"packages/shared/dist/schemas/auth.js.map":{"size":981,"mtime_nanos":1783332897741022052,"mode":436,"is_dir":false},"packages/shared/dist/schemas/message.d.ts":{"size":1786,"mtime_nanos":1783320793372004947,"mode":436,"is_dir":false},"packages/shared/dist/schemas/memory.d.ts.map":{"size":479,"mtime_nanos":1783332897784397531,"mode":436,"is_dir":false},"packages/shared/dist/schemas/report.js":{"size":450,"mtime_nanos":1783332897785397534,"mode":436,"is_dir":false},"packages/shared/dist/schemas/settings.js.map":{"size":720,"mtime_nanos":1783332897796397564,"mode":436,"is_dir":false},"packages/shared/dist/schemas/voice.d.ts.map":{"size":474,"mtime_nanos":1783332897773880897,"mode":436,"is_dir":false},"packages/shared/dist/schemas/file.d.ts":{"size":1220,"mtime_nanos":1783320793374004956,"mode":436,"is_dir":false},"packages/shared/dist/schemas/index.js":{"size":290,"mtime_nanos":1783332897800397575,"mode":436,"is_dir":false}},"order":["packages/shared/.turbo/turbo-build.log","packages/shared/dist/index.d.ts","packages/shared/dist/index.d.ts.map","packages/shared/dist/index.js","packages/shared/dist/index.js.map","packages/shared/dist/schemas/ai.d.ts","packages/shared/dist/schemas/ai.d.ts.map","packages/shared/dist/schemas/ai.js","packages/shared/dist/schemas/ai.js.map","packages/shared/dist/schemas/auth.d.ts","packages/shared/dist/schemas/auth.d.ts.map","packages/shared/dist/schemas/auth.js","packages/shared/dist/schemas/auth.js.map","packages/shared/dist/schemas/file.d.ts","packages/shared/dist/schemas/file.d.ts.map","packages/shared/dist/schemas/file.js","packages/shared/dist/schemas/file.js.map","packages/shared/dist/schemas/index.d.ts","packages/shared/dist/schemas/index.d.ts.map","packages/shared/dist/schemas/index.js","packages/shared/dist/schemas/index.js.map","packages/shared/dist/schemas/memory.d.ts","packages/shared/dist/schemas/memory.d.ts.map","packages/shared/dist/schemas/memory.js","packages/shared/dist/schemas/memory.js.map","packages/shared/dist/schemas/message.d.ts","packages/shared/dist/schemas/message.d.ts.map","packages/shared/dist/schemas/message.js","packages/shared/dist/schemas/message.js.map","packages/shared/dist/schemas/platform.d.ts","packages/shared/dist/schemas/platform.d.ts.map","packages/shared/dist/schemas/platform.js","packages/shared/dist/schemas/platform.js.map","packages/shared/dist/schemas/report.d.ts","packages/shared/dist/schemas/report.d.ts.map","packages/shared/dist/schemas/report.js","packages/shared/dist/schemas/report.js.map","packages/shared/dist/schemas/settings.d.ts","packages/shared/dist/schemas/settings.d.ts.map","packages/shared/dist/schemas/settings.js","packages/shared/dist/schemas/settings.js.map","packages/shared/dist/schemas/voice.d.ts","packages/shared/dist/schemas/voice.d.ts.map","packages/shared/dist/schemas/voice.js","packages/shared/dist/schemas/voice.js.map","packages/shared/dist/types/index.d.ts","packages/shared/dist/types/index.d.ts.map","packages/shared/dist/types/index.js","packages/shared/dist/types/index.js.map"]}